tinydb_jsonorm/models.py~
tinydb_jsonorm/db.py~
tinydb_jsonorm/models.py
tinydb_jsonorm/__init__.py~
tinydb_jsonorm/cuid.py
tinydb_jsonorm/db.py
tinydb_jsonorm/__init__.py
tinydb_jsonorm-0.2.1.dist-info/DESCRIPTION.rst
tinydb_jsonorm-0.2.1.dist-info/METADATA
tinydb_jsonorm-0.2.1.dist-info/metadata.json
tinydb_jsonorm-0.2.1.dist-info/RECORD
tinydb_jsonorm-0.2.1.dist-info/WHEEL
tinydb_jsonorm-0.2.1.dist-info/top_level.txt
