Metadata-Version: 2.0
Name: tinydb-jsonorm
Version: 0.2.1
Summary: A library based on jsonmodels that adds some ORM features and another few conveniences to TinyDB with Json storage and tinydb-smartcache enabled.
Home-page: https://github.com/abnerjacobsen/tinydb-jsonorm
Author: Abner G Jacobsen
Author-email: abner@apoana.com.br
License: BSD
Keywords: TinyDB ORM jsonmodels Json
Platform: UNKNOWN
Classifier: Development Status :: 5 - Production/Stable
Classifier: Intended Audience :: Developers
Classifier: License :: OSI Approved :: BSD License
Classifier: Operating System :: Unix
Classifier: Operating System :: POSIX
Classifier: Operating System :: Microsoft :: Windows
Classifier: Programming Language :: Python
Classifier: Programming Language :: Python :: 2.7
Classifier: Programming Language :: Python :: 3
Classifier: Programming Language :: Python :: 3.3
Classifier: Programming Language :: Python :: 3.4
Classifier: Programming Language :: Python :: 3.5
Classifier: Programming Language :: Python :: Implementation :: CPython
Classifier: Programming Language :: Python :: Implementation :: PyPy
Classifier: Topic :: Utilities
Requires-Dist: tinydb (>=3.2.0)
Requires-Dist: tinydb-serialization (>=1.0.3)
Requires-Dist: tinydb-smartcache (>=1.0.2)
Requires-Dist: jsonmodels (>=2.1.2)
